agi_med_metrics/__init__.py
agi_med_metrics/errors_cv.py
agi_med_metrics/errors_ml.py
agi_med_metrics/errors_nlp.py
agi_med_metrics-0.0.7.dist-info/METADATA
agi_med_metrics-0.0.7.dist-info/WHEEL
agi_med_metrics-0.0.7.dist-info/top_level.txt
agi_med_metrics-0.0.7.dist-info/RECORD
